README.md
setup.py
way2package2/__init__.py
way2package2/class1.py
way2package2.egg-info/PKG-INFO
way2package2.egg-info/SOURCES.txt
way2package2.egg-info/dependency_links.txt
way2package2.egg-info/top_level.txt